nvidia_fan_control/__init__.py
nvidia_fan_control/app.py
nvidia_fan_control/nvidiafancontrol.py
nvidia_fan_control/settings.py
nvidia_fan_control-1.0.6.data/data/lib/python3.8/dist-packages/nvidia_fan_control/font.css
nvidia_fan_control-1.0.6.data/data/lib/python3.8/dist-packages/share/locale/en/LC_MESSAGES/nvidiafancontrol.mo
nvidia_fan_control-1.0.6.data/data/lib/python3.8/dist-packages/share/locale/it/LC_MESSAGES/nvidiafancontrol.mo
nvidia_fan_control-1.0.6.data/data/share/applications/nvidiafancontrol.desktop
nvidia_fan_control-1.0.6.data/data/share/pixmaps/nvidiafancontrol.svg
nvidia_fan_control-1.0.6.dist-info/LICENSE
nvidia_fan_control-1.0.6.dist-info/METADATA
nvidia_fan_control-1.0.6.dist-info/WHEEL
nvidia_fan_control-1.0.6.dist-info/entry_points.txt
nvidia_fan_control-1.0.6.dist-info/top_level.txt
nvidia_fan_control-1.0.6.dist-info/RECORD
