Metadata-Version: 2.1
Name: nvidia-fan-control
Version: 1.0.6
Summary: Nvidia Fan Control
Home-page: https://github.com/tudo75/nvidia-fan-control
Author: Nicola Tudino
Author-email: tudo75@gmail.com
License: GNU General Public License v3.0
Project-URL: Bug Tracker, https://github.com/tudo75/nvidia-fan-control/issues
Keywords: nvidia fan control gui linux gpu speed
Platform: UNKNOWN
Classifier: Development Status :: 5 - Production/Stable
Classifier: Environment :: X11 Applications :: GTK
Classifier: Topic :: Utilities
Classifier: Intended Audience :: End Users/Desktop
Classifier: Operating System :: POSIX :: Linux
Classifier: Programming Language :: Python :: 3.8
Classifier: License :: OSI Approved :: GNU General Public License v3 (GPLv3)
License-File: LICENSE
Requires-Dist: pycairo (>=1.20.1)
Requires-Dist: pygobject (>=3.36.0)
